bountylab/__init__.py
bountylab/_base_client.py
bountylab/_client.py
bountylab/_compat.py
bountylab/_constants.py
bountylab/_exceptions.py
bountylab/_files.py
bountylab/_models.py
bountylab/_qs.py
bountylab/_resource.py
bountylab/_response.py
bountylab/_streaming.py
bountylab/_types.py
bountylab/_version.py
bountylab/py.typed
bountylab/_utils/__init__.py
bountylab/_utils/_compat.py
bountylab/_utils/_datetime_parse.py
bountylab/_utils/_json.py
bountylab/_utils/_logs.py
bountylab/_utils/_proxy.py
bountylab/_utils/_reflection.py
bountylab/_utils/_resources_proxy.py
bountylab/_utils/_streams.py
bountylab/_utils/_sync.py
bountylab/_utils/_transform.py
bountylab/_utils/_typing.py
bountylab/_utils/_utils.py
bountylab/lib/.keep
bountylab/resources/__init__.py
bountylab/resources/raw_repos.py
bountylab/resources/raw_users.py
bountylab/resources/search_repos.py
bountylab/resources/search_users.py
bountylab/resources/user_emails.py
bountylab/types/__init__.py
bountylab/types/raw_repo_by_fullname_params.py
bountylab/types/raw_repo_by_fullname_response.py
bountylab/types/raw_repo_count_params.py
bountylab/types/raw_repo_count_response.py
bountylab/types/raw_repo_graph_params.py
bountylab/types/raw_repo_graph_response.py
bountylab/types/raw_repo_retrieve_params.py
bountylab/types/raw_repo_retrieve_response.py
bountylab/types/raw_user_by_login_params.py
bountylab/types/raw_user_by_login_response.py
bountylab/types/raw_user_count_params.py
bountylab/types/raw_user_count_response.py
bountylab/types/raw_user_graph_params.py
bountylab/types/raw_user_graph_response.py
bountylab/types/raw_user_retrieve_params.py
bountylab/types/raw_user_retrieve_response.py
bountylab/types/search_repo_natural_language_params.py
bountylab/types/search_repo_natural_language_response.py
bountylab/types/search_repo_search_params.py
bountylab/types/search_repo_search_response.py
bountylab/types/search_user_natural_language_params.py
bountylab/types/search_user_natural_language_response.py
bountylab-0.35.0.dist-info/METADATA
bountylab-0.35.0.dist-info/WHEEL
bountylab-0.35.0.dist-info/licenses/LICENSE
bountylab-0.35.0.dist-info/RECORD
